{
    "packages": {
        "lofi/backup": [
            {
                "name": "lofi/backup",
                "version": "v3.3.4",
                "version_normalized": "3.3.4.0",
                "source": {
                    "type": "git",
                    "url": "git@github.com:ncortex/lofi-backup.git",
                    "reference": "f2235f8983f303b524c773f3d4063b29cf11085b"
                },
                "dist": {
                    "type": "zip",
                    "url": "https://api.github.com/repos/ncortex/lofi-backup/zipball/f2235f8983f303b524c773f3d4063b29cf11085b",
                    "reference": "f2235f8983f303b524c773f3d4063b29cf11085b",
                    "shasum": ""
                },
                "require": {
                    "illuminate/support": "^10.0|^11.0|^12.0",
                    "lofi/kernel": "^3.3",
                    "lofi/ui": "^3.3",
                    "php": "^8.2"
                },
                "require-dev": {
                    "orchestra/testbench": "^8.0|^9.0|^10.0",
                    "phpunit/phpunit": "^10.0|^11.0"
                },
                "time": "2026-02-09T11:37:53+00:00",
                "type": "library",
                "extra": {
                    "laravel": {
                        "providers": [
                            "Lofi\\Backup\\BackupServiceProvider"
                        ]
                    },
                    "lofi": {
                        "category": "devtool"
                    }
                },
                "autoload": {
                    "psr-4": {
                        "Lofi\\Backup\\": "src/"
                    }
                },
                "autoload-dev": {
                    "psr-4": {
                        "Lofi\\Backup\\Tests\\": "tests/"
                    }
                },
                "license": [
                    "MIT"
                ],
                "authors": [
                    {
                        "name": "Lofi Framework",
                        "email": "hello@lofi.dev"
                    }
                ],
                "description": "Backup and Restore System for Lofi Framework",
                "support": {
                    "source": "https://github.com/ncortex/lofi-backup/tree/v3.3.4",
                    "issues": "https://github.com/ncortex/lofi-backup/issues"
                }
            },
            {
                "name": "lofi/backup",
                "version": "v3.3.5",
                "version_normalized": "3.3.5.0",
                "source": {
                    "type": "git",
                    "url": "git@github.com:ncortex/lofi-backup.git",
                    "reference": "3eeef40a7879d2e670e5e0a20c47c4a5687ee0a9"
                },
                "dist": {
                    "type": "zip",
                    "url": "https://api.github.com/repos/ncortex/lofi-backup/zipball/3eeef40a7879d2e670e5e0a20c47c4a5687ee0a9",
                    "reference": "3eeef40a7879d2e670e5e0a20c47c4a5687ee0a9",
                    "shasum": ""
                },
                "require": {
                    "illuminate/support": "^10.0|^11.0|^12.0",
                    "lofi/kernel": "^3.0",
                    "lofi/ui": "^3.0",
                    "php": "^8.2"
                },
                "require-dev": {
                    "orchestra/testbench": "^8.0|^9.0|^10.0",
                    "phpunit/phpunit": "^10.0|^11.0"
                },
                "time": "2026-02-08T10:02:08+00:00",
                "type": "library",
                "extra": {
                    "laravel": {
                        "providers": [
                            "Lofi\\Backup\\BackupServiceProvider"
                        ]
                    },
                    "lofi": {
                        "category": "devtool"
                    }
                },
                "autoload": {
                    "psr-4": {
                        "Lofi\\Backup\\": "src/"
                    }
                },
                "autoload-dev": {
                    "psr-4": {
                        "Lofi\\Backup\\Tests\\": "tests/"
                    }
                },
                "license": [
                    "MIT"
                ],
                "authors": [
                    {
                        "name": "Lofi Framework",
                        "email": "hello@lofi.dev"
                    }
                ],
                "description": "Backup and Restore System for Lofi Framework",
                "support": {
                    "source": "https://github.com/ncortex/lofi-backup/tree/v3.3.5",
                    "issues": "https://github.com/ncortex/lofi-backup/issues"
                }
            }
        ]
    }
}
